xarray_dataclasses/__about__.py
xarray_dataclasses/__init__.py
xarray_dataclasses/dataarray.py
xarray_dataclasses/datamodel.py
xarray_dataclasses/dataoptions.py
xarray_dataclasses/dataset.py
xarray_dataclasses/py.typed
xarray_dataclasses/typing.py
xarray_dataclass-2.0.0.dist-info/METADATA
xarray_dataclass-2.0.0.dist-info/WHEEL
xarray_dataclass-2.0.0.dist-info/licenses/LICENSE
xarray_dataclass-2.0.0.dist-info/RECORD
