Metadata-Version: 2.4
Name: xarray-dataclass
Version: 2.0.0
Summary: xarray data creation by data classes
Project-URL: Homepage, https://github.com/xarray-contrib/xarray-dataclasses/
Project-URL: Repository, https://github.com/xarray-contrib/xarray-dataclasses/
Project-URL: Documentation, https://xarray-contrib.github.io/xarray-dataclasses/
Author-email: Akio Taniguchi <taniguchi.akio@gmail.com>, Wouter-Michiel Vierdag <michiel.vierdag@scverse.org>
Maintainer-email: Wouter-Michiel Vierdag <michiel.vierdag@scverse.org>
License: MIT License
License-File: LICENSE
Keywords: dataarray,dataclass,dataset,typing,xarray
Classifier: License :: OSI Approved :: MIT License
Classifier: Programming Language :: Python :: 3
Classifier: Programming Language :: Python :: 3.9
Classifier: Programming Language :: Python :: 3.10
Classifier: Programming Language :: Python :: 3.11
Classifier: Programming Language :: Python :: 3.12
Classifier: Programming Language :: Python :: 3.13
Requires-Python: >=3.9
Requires-Dist: numpy>=2.0.0
Requires-Dist: typing-extensions>=4.10.0
Requires-Dist: xarray>=2022.3
Provides-Extra: dev
Requires-Dist: myst-parser>=3.0; extra == 'dev'
Requires-Dist: pre-commit>=4.2.0; extra == 'dev'
Requires-Dist: pydata-sphinx-theme>=0.14; extra == 'dev'
Requires-Dist: pytest>=8.2; extra == 'dev'
Requires-Dist: sphinx>=7.1; extra == 'dev'
